minigun/__init__.py
minigun/__main__.py
minigun/arbitrary.py
minigun/budget.py
minigun/cardinality.py
minigun/cli.py
minigun/domain.py
minigun/generate.py
minigun/orchestrator.py
minigun/order.py
minigun/pretty.py
minigun/py.typed
minigun/reporter.py
minigun/sample.py
minigun/search.py
minigun/shrink.py
minigun/specify.py
minigun/stream.py
minigun/util.py
minigun_soren_n-2.4.2.dist-info/METADATA
minigun_soren_n-2.4.2.dist-info/WHEEL
minigun_soren_n-2.4.2.dist-info/entry_points.txt
minigun_soren_n-2.4.2.dist-info/licenses/LICENSE
minigun_soren_n-2.4.2.dist-info/RECORD
