Metadata-Version: 2.4
Name: minigun-soren-n
Version: 2.4.2
Summary: A library for property-based testing of Python programs
Project-URL: Repository, https://github.com/soren-n/minigun
Project-URL: Documentation, https://minigun.readthedocs.io/en/stable/
Project-URL: Bug Tracker, https://github.com/soren-n/minigun/issues
Author-email: Soren Norbaek <sorennorbaek@gmail.com>
License:                     GNU GENERAL PUBLIC LICENSE
License-File: LICENSE
Keywords: property-based testing,python,testing
Classifier: Environment :: Console
Classifier: Intended Audience :: Developers
Classifier: License :: OSI Approved :: GNU General Public License v3 (GPLv3)
Classifier: Operating System :: OS Independent
Classifier: Programming Language :: Python :: 3
Classifier: Programming Language :: Python :: 3.12
Requires-Python: >=3.12
Requires-Dist: returns>=0.25.0
Requires-Dist: rich>=13.0.0
Requires-Dist: tqdm>=4.67.1
Requires-Dist: typeset-soren-n>=2.0.8
